{
  "generated_at": "2026-06-21T12:56:32.402843+08:00",
  "total_titles_processed": 647,
  "failed_sources": [],
  "trends": [
    {
      "keyword_group": "谷歌 google gemini vibe coding",
      "match_count": 1,
      "titles": [
        {
          "title": "学习英伟达“好榜样”，谷歌和博通都开始“有样学样”，开启“AI芯片闭环”",
          "url": "https://wallstreetcn.com/articles/3775105",
          "source": "华尔街见闻",
          "ranks": [
            9
          ],
          "is_new": false,
          "appearance_count": 2,
          "time_info": "[07时15分 ~ 07时16分]"
        }
      ]
    }
  ],
  "report_image_url": "https://hkhongzhen.github.io/TrendRadar/img/news.jpg"
}